chenyutong/__init__.py
chenyutong/getall.py
chenyutong-0.0.1.dist-info/METADATA
chenyutong-0.0.1.dist-info/WHEEL
chenyutong-0.0.1.dist-info/top_level.txt
chenyutong-0.0.1.dist-info/RECORD
