Metadata-Version: 2.1
Name: chenyutong
Version: 0.0.1
Summary: This is me xiajibaxiede
Home-page: https://github.com/sunjian-github/ezface
Author: chenyutong
Author-email: 2463400852@qq.com
